paranestamol/LoadWindow.qml
paranestamol/Manipulator.qml
paranestamol/PlotSelector.qml
paranestamol/__init__.py
paranestamol/__main__.py
paranestamol/plt_managers.py
paranestamol/samples_model.py
paranestamol/utils.js
paranestamol/utils.py
paranestamol/view.qml
paranestamol-0.0.12.dist-info/LICENSE.txt
paranestamol-0.0.12.dist-info/METADATA
paranestamol-0.0.12.dist-info/WHEEL
paranestamol-0.0.12.dist-info/top_level.txt
paranestamol-0.0.12.dist-info/RECORD
