Metadata-Version: 2.1
Name: paranestamol
Version: 0.0.12
Summary: A QtQuick-based nested sampling visualisation tool.
Home-page: https://github.com/appetrosyan/paranestamol
Author: Aleksandr Petrosyan
Author-email: a-p-petrosyan@yandex.ru
License: MIT
Platform: UNKNOWN
Classifier: License :: OSI Approved :: MIT License
Classifier: Development Status :: 4 - Beta
Classifier: Intended Audience :: Science/Research
Requires-Dist: matplotlib-backend-qtquick
Requires-Dist: anesthetic
Requires-Dist: pyside2
Requires-Dist: numpy
Requires-Dist: matplotlib
